ssc_codegen/__init__.py
ssc_codegen/_compat.py
ssc_codegen/compiler.py
ssc_codegen/document.py
ssc_codegen/document_utlis.py
ssc_codegen/json_struct.py
ssc_codegen/json_to_scc.py
ssc_codegen/logs.py
ssc_codegen/pseudo_selectors.py
ssc_codegen/schema.py
ssc_codegen/selector_utils.py
ssc_codegen/str_utils.py
ssc_codegen/tokens.py
ssc_codegen/ast_/__init__.py
ssc_codegen/ast_/base.py
ssc_codegen/ast_/nodes_array.py
ssc_codegen/ast_/nodes_cast.py
ssc_codegen/ast_/nodes_core.py
ssc_codegen/ast_/nodes_filter.py
ssc_codegen/ast_/nodes_selectors.py
ssc_codegen/ast_/nodes_string.py
ssc_codegen/ast_/nodes_validate.py
ssc_codegen/ast_build/__init__.py
ssc_codegen/ast_build/builder.py
ssc_codegen/ast_build/main.py
ssc_codegen/ast_build/utils.py
ssc_codegen/ast_grep_rules/js_rules.yml
ssc_codegen/ast_grep_rules/py_drop_prefix_suffix_backport.yml
ssc_codegen/ast_grep_rules/py_rules.yml
ssc_codegen/cli/__init__.py
ssc_codegen/cli/ast_grep.py
ssc_codegen/cli/cli_callbacks.py
ssc_codegen/cli/cli_utils.py
ssc_codegen/cli/code_callbacks.py
ssc_codegen/cli/consts.py
ssc_codegen/cli/main.py
ssc_codegen/cli/runtime_parse_runners.py
ssc_codegen/converters/__init__.py
ssc_codegen/converters/base.py
ssc_codegen/converters/go_goquery.py
ssc_codegen/converters/helpers.py
ssc_codegen/converters/js_pure.py
ssc_codegen/converters/lua_htmlparser.py
ssc_codegen/converters/py_base.py
ssc_codegen/converters/py_bs4.py
ssc_codegen/converters/py_lxml.py
ssc_codegen/converters/py_parsel.py
ssc_codegen/converters/py_selectolax.py
ssc_codegen/converters/templates/__init__.py
ssc_codegen/converters/templates/go_goquery.py
ssc_codegen/converters/templates/js_pure.py
ssc_codegen/converters/templates/lua_base.py
ssc_codegen/converters/templates/lua_css_compat.py
ssc_codegen/converters/templates/lua_re_compat.py
ssc_codegen/converters/templates/py_base.py
ssc_codegen/static_checker/__init__.py
ssc_codegen/static_checker/base.py
ssc_codegen/static_checker/callbacks.py
ssc_codegen-0.13.4.dist-info/METADATA
ssc_codegen-0.13.4.dist-info/WHEEL
ssc_codegen-0.13.4.dist-info/entry_points.txt
ssc_codegen-0.13.4.dist-info/licenses/LICENSE
ssc_codegen-0.13.4.dist-info/RECORD
