Metadata-Version: 2.4
Name: ssc_codegen
Version: 0.13.4
Summary: Python-dsl code converter to html parser for web scraping 
Project-URL: Documentation, https://github.com/vypivshiy/selector_schema_codegen#readme
Project-URL: Issues, https://github.com/vypivshiy/selector_schema_codegen/issues
Project-URL: Source, https://github.com/vypivshiy/selector_schema_codegen
Project-URL: Examples, https://github.com/vypivshiy/selector_schema_codegen/examples
License-File: LICENSE
Classifier: Development Status :: 3 - Alpha
Classifier: Environment :: Console
Classifier: Intended Audience :: Developers
Classifier: License :: OSI Approved :: MIT License
Classifier: Programming Language :: Python :: 3.10
Classifier: Programming Language :: Python :: 3.11
Classifier: Programming Language :: Python :: 3.12
Classifier: Programming Language :: Python :: 3.13
Classifier: Topic :: Software Development :: Code Generators
Classifier: Topic :: Text Processing :: Markup :: HTML
Classifier: Topic :: Utilities
Requires-Python: >=3.10
Requires-Dist: ast-grep-cli>=0.38.1
Requires-Dist: bs4>=0.0.2
Requires-Dist: click<8.2.0
Requires-Dist: colorama>=0.4.6; sys_platform == 'win32'
Requires-Dist: cssselect>=1.2.0
Requires-Dist: httpx>=0.28.1
Requires-Dist: ichrome>=4.0.4
Requires-Dist: lxml>=5.3.0
Requires-Dist: soupsieve>=2.6
Requires-Dist: tinycss2>=1.4.0
Requires-Dist: typer>=0.15.1
Requires-Dist: typing-extensions; python_version < '3.11'
